<annotation>
	<folder></folder>
	<filename>031380916_jpg.rf.cb33a371014780ef9c089535a90e8a81.jpg</filename>
	<path>031380916_jpg.rf.cb33a371014780ef9c089535a90e8a81.jpg</path>
	<source>
		<database>roboflow.ai</database>
	</source>
	<size>
		<width>416</width>
		<height>416</height>
		<depth>3</depth>
	</size>
	<segmented>0</segmented>
	<object>
		<name>3</name>
		<pose>Unspecified</pose>
		<truncated>0</truncated>
		<difficult>0</difficult>
		<occluded>0</occluded>
		<bndbox>
			<xmin>97</xmin>
			<xmax>126</xmax>
			<ymin>44</ymin>
			<ymax>78</ymax>
		</bndbox>
	</object>
	<object>
		<name>5</name>
		<pose>Unspecified</pose>
		<truncated>0</truncated>
		<difficult>0</difficult>
		<occluded>0</occluded>
		<bndbox>
			<xmin>132</xmin>
			<xmax>167</xmax>
			<ymin>58</ymin>
			<ymax>94</ymax>
		</bndbox>
	</object>
	<object>
		<name>12</name>
		<pose>Unspecified</pose>
		<truncated>0</truncated>
		<difficult>0</difficult>
		<occluded>0</occluded>
		<bndbox>
			<xmin>170</xmin>
			<xmax>210</xmax>
			<ymin>90</ymin>
			<ymax>119</ymax>
		</bndbox>
	</object>
</annotation>
