<annotation>
	<folder></folder>
	<filename>076764369_jpg.rf.6689d2ccaaae3b73b93530aa08ad560c.jpg</filename>
	<path>076764369_jpg.rf.6689d2ccaaae3b73b93530aa08ad560c.jpg</path>
	<source>
		<database>roboflow.ai</database>
	</source>
	<size>
		<width>416</width>
		<height>416</height>
		<depth>3</depth>
	</size>
	<segmented>0</segmented>
	<object>
		<name>11</name>
		<pose>Unspecified</pose>
		<truncated>0</truncated>
		<difficult>0</difficult>
		<occluded>0</occluded>
		<bndbox>
			<xmin>191</xmin>
			<xmax>215</xmax>
			<ymin>198</ymin>
			<ymax>221</ymax>
		</bndbox>
	</object>
	<object>
		<name>3</name>
		<pose>Unspecified</pose>
		<truncated>0</truncated>
		<difficult>0</difficult>
		<occluded>0</occluded>
		<bndbox>
			<xmin>216</xmin>
			<xmax>240</xmax>
			<ymin>210</ymin>
			<ymax>235</ymax>
		</bndbox>
	</object>
	<object>
		<name>3</name>
		<pose>Unspecified</pose>
		<truncated>0</truncated>
		<difficult>0</difficult>
		<occluded>0</occluded>
		<bndbox>
			<xmin>236</xmin>
			<xmax>260</xmax>
			<ymin>228</ymin>
			<ymax>252</ymax>
		</bndbox>
	</object>
</annotation>
