<annotation>
	<folder></folder>
	<filename>168760368_jpg.rf.956733b27ca54e55e8c28b43c7a91394.jpg</filename>
	<path>168760368_jpg.rf.956733b27ca54e55e8c28b43c7a91394.jpg</path>
	<source>
		<database>roboflow.ai</database>
	</source>
	<size>
		<width>416</width>
		<height>416</height>
		<depth>3</depth>
	</size>
	<segmented>0</segmented>
	<object>
		<name>12</name>
		<pose>Unspecified</pose>
		<truncated>0</truncated>
		<difficult>0</difficult>
		<occluded>0</occluded>
		<bndbox>
			<xmin>135</xmin>
			<xmax>158</xmax>
			<ymin>118</ymin>
			<ymax>139</ymax>
		</bndbox>
	</object>
	<object>
		<name>6</name>
		<pose>Unspecified</pose>
		<truncated>0</truncated>
		<difficult>0</difficult>
		<occluded>0</occluded>
		<bndbox>
			<xmin>158</xmin>
			<xmax>179</xmax>
			<ymin>126</ymin>
			<ymax>150</ymax>
		</bndbox>
	</object>
	<object>
		<name>1</name>
		<pose>Unspecified</pose>
		<truncated>0</truncated>
		<difficult>0</difficult>
		<occluded>0</occluded>
		<bndbox>
			<xmin>190</xmin>
			<xmax>210</xmax>
			<ymin>151</ymin>
			<ymax>173</ymax>
		</bndbox>
	</object>
</annotation>
