<annotation>
	<folder></folder>
	<filename>203168364_jpg.rf.b620b3ed185ec08625ac0a958b5ae95f.jpg</filename>
	<path>203168364_jpg.rf.b620b3ed185ec08625ac0a958b5ae95f.jpg</path>
	<source>
		<database>roboflow.ai</database>
	</source>
	<size>
		<width>416</width>
		<height>416</height>
		<depth>3</depth>
	</size>
	<segmented>0</segmented>
	<object>
		<name>7</name>
		<pose>Unspecified</pose>
		<truncated>0</truncated>
		<difficult>0</difficult>
		<occluded>0</occluded>
		<bndbox>
			<xmin>240</xmin>
			<xmax>271</xmax>
			<ymin>128</ymin>
			<ymax>164</ymax>
		</bndbox>
	</object>
	<object>
		<name>6</name>
		<pose>Unspecified</pose>
		<truncated>0</truncated>
		<difficult>0</difficult>
		<occluded>0</occluded>
		<bndbox>
			<xmin>268</xmin>
			<xmax>304</xmax>
			<ymin>156</ymin>
			<ymax>192</ymax>
		</bndbox>
	</object>
	<object>
		<name>4</name>
		<pose>Unspecified</pose>
		<truncated>0</truncated>
		<difficult>0</difficult>
		<occluded>0</occluded>
		<bndbox>
			<xmin>302</xmin>
			<xmax>339</xmax>
			<ymin>202</ymin>
			<ymax>231</ymax>
		</bndbox>
	</object>
</annotation>
