<annotation>
	<folder></folder>
	<filename>218134454_jpg.rf.40bcc03be91ad26775ec4ec4f792a418.jpg</filename>
	<path>218134454_jpg.rf.40bcc03be91ad26775ec4ec4f792a418.jpg</path>
	<source>
		<database>roboflow.ai</database>
	</source>
	<size>
		<width>416</width>
		<height>416</height>
		<depth>3</depth>
	</size>
	<segmented>0</segmented>
	<object>
		<name>11</name>
		<pose>Unspecified</pose>
		<truncated>0</truncated>
		<difficult>0</difficult>
		<occluded>0</occluded>
		<bndbox>
			<xmin>150</xmin>
			<xmax>187</xmax>
			<ymin>173</ymin>
			<ymax>206</ymax>
		</bndbox>
	</object>
	<object>
		<name>5</name>
		<pose>Unspecified</pose>
		<truncated>0</truncated>
		<difficult>0</difficult>
		<occluded>0</occluded>
		<bndbox>
			<xmin>183</xmin>
			<xmax>221</xmax>
			<ymin>196</ymin>
			<ymax>232</ymax>
		</bndbox>
	</object>
	<object>
		<name>12</name>
		<pose>Unspecified</pose>
		<truncated>0</truncated>
		<difficult>0</difficult>
		<occluded>0</occluded>
		<bndbox>
			<xmin>208</xmin>
			<xmax>250</xmax>
			<ymin>232</ymin>
			<ymax>257</ymax>
		</bndbox>
	</object>
</annotation>
