<annotation>
	<folder></folder>
	<filename>228027344_jpg.rf.533acad7999e34570d2399192fd40ea6.jpg</filename>
	<path>228027344_jpg.rf.533acad7999e34570d2399192fd40ea6.jpg</path>
	<source>
		<database>roboflow.ai</database>
	</source>
	<size>
		<width>416</width>
		<height>416</height>
		<depth>3</depth>
	</size>
	<segmented>0</segmented>
	<object>
		<name>14</name>
		<pose>Unspecified</pose>
		<truncated>0</truncated>
		<difficult>0</difficult>
		<occluded>0</occluded>
		<bndbox>
			<xmin>90</xmin>
			<xmax>122</xmax>
			<ymin>62</ymin>
			<ymax>94</ymax>
		</bndbox>
	</object>
	<object>
		<name>3</name>
		<pose>Unspecified</pose>
		<truncated>0</truncated>
		<difficult>0</difficult>
		<occluded>0</occluded>
		<bndbox>
			<xmin>119</xmin>
			<xmax>149</xmax>
			<ymin>67</ymin>
			<ymax>101</ymax>
		</bndbox>
	</object>
	<object>
		<name>11</name>
		<pose>Unspecified</pose>
		<truncated>0</truncated>
		<difficult>0</difficult>
		<occluded>0</occluded>
		<bndbox>
			<xmin>165</xmin>
			<xmax>202</xmax>
			<ymin>91</ymin>
			<ymax>124</ymax>
		</bndbox>
	</object>
</annotation>
