<annotation>
	<folder></folder>
	<filename>301012240_jpg.rf.ee35aa494375ad64188eed73e97b047c.jpg</filename>
	<path>301012240_jpg.rf.ee35aa494375ad64188eed73e97b047c.jpg</path>
	<source>
		<database>roboflow.ai</database>
	</source>
	<size>
		<width>416</width>
		<height>416</height>
		<depth>3</depth>
	</size>
	<segmented>0</segmented>
	<object>
		<name>10</name>
		<pose>Unspecified</pose>
		<truncated>0</truncated>
		<difficult>0</difficult>
		<occluded>0</occluded>
		<bndbox>
			<xmin>220</xmin>
			<xmax>245</xmax>
			<ymin>77</ymin>
			<ymax>99</ymax>
		</bndbox>
	</object>
	<object>
		<name>9</name>
		<pose>Unspecified</pose>
		<truncated>0</truncated>
		<difficult>0</difficult>
		<occluded>0</occluded>
		<bndbox>
			<xmin>243</xmin>
			<xmax>266</xmax>
			<ymin>92</ymin>
			<ymax>116</ymax>
		</bndbox>
	</object>
	<object>
		<name>14</name>
		<pose>Unspecified</pose>
		<truncated>0</truncated>
		<difficult>0</difficult>
		<occluded>0</occluded>
		<bndbox>
			<xmin>259</xmin>
			<xmax>288</xmax>
			<ymin>114</ymin>
			<ymax>135</ymax>
		</bndbox>
	</object>
</annotation>
