<annotation>
	<folder></folder>
	<filename>335468953_jpg.rf.3964eb8bf3f14e940557fed74c22fb43.jpg</filename>
	<path>335468953_jpg.rf.3964eb8bf3f14e940557fed74c22fb43.jpg</path>
	<source>
		<database>roboflow.ai</database>
	</source>
	<size>
		<width>416</width>
		<height>416</height>
		<depth>3</depth>
	</size>
	<segmented>0</segmented>
	<object>
		<name>1</name>
		<pose>Unspecified</pose>
		<truncated>0</truncated>
		<difficult>0</difficult>
		<occluded>0</occluded>
		<bndbox>
			<xmin>62</xmin>
			<xmax>90</xmax>
			<ymin>230</ymin>
			<ymax>262</ymax>
		</bndbox>
	</object>
	<object>
		<name>14</name>
		<pose>Unspecified</pose>
		<truncated>0</truncated>
		<difficult>0</difficult>
		<occluded>0</occluded>
		<bndbox>
			<xmin>102</xmin>
			<xmax>130</xmax>
			<ymin>214</ymin>
			<ymax>252</ymax>
		</bndbox>
	</object>
	<object>
		<name>4</name>
		<pose>Unspecified</pose>
		<truncated>0</truncated>
		<difficult>0</difficult>
		<occluded>0</occluded>
		<bndbox>
			<xmin>148</xmin>
			<xmax>178</xmax>
			<ymin>210</ymin>
			<ymax>243</ymax>
		</bndbox>
	</object>
</annotation>
