<annotation>
	<folder></folder>
	<filename>391665379_jpg.rf.5525d3914eacca456348d8902b275ecb.jpg</filename>
	<path>391665379_jpg.rf.5525d3914eacca456348d8902b275ecb.jpg</path>
	<source>
		<database>roboflow.ai</database>
	</source>
	<size>
		<width>416</width>
		<height>416</height>
		<depth>3</depth>
	</size>
	<segmented>0</segmented>
	<object>
		<name>3</name>
		<pose>Unspecified</pose>
		<truncated>0</truncated>
		<difficult>0</difficult>
		<occluded>0</occluded>
		<bndbox>
			<xmin>226</xmin>
			<xmax>251</xmax>
			<ymin>185</ymin>
			<ymax>210</ymax>
		</bndbox>
	</object>
	<object>
		<name>4</name>
		<pose>Unspecified</pose>
		<truncated>0</truncated>
		<difficult>0</difficult>
		<occluded>0</occluded>
		<bndbox>
			<xmin>243</xmin>
			<xmax>268</xmax>
			<ymin>210</ymin>
			<ymax>231</ymax>
		</bndbox>
	</object>
	<object>
		<name>8</name>
		<pose>Unspecified</pose>
		<truncated>0</truncated>
		<difficult>0</difficult>
		<occluded>0</occluded>
		<bndbox>
			<xmin>255</xmin>
			<xmax>280</xmax>
			<ymin>228</ymin>
			<ymax>252</ymax>
		</bndbox>
	</object>
</annotation>
