<annotation>
	<folder></folder>
	<filename>481432741_jpg.rf.a0c945629729fde5b5c3a1017dab8989.jpg</filename>
	<path>481432741_jpg.rf.a0c945629729fde5b5c3a1017dab8989.jpg</path>
	<source>
		<database>roboflow.ai</database>
	</source>
	<size>
		<width>416</width>
		<height>416</height>
		<depth>3</depth>
	</size>
	<segmented>0</segmented>
	<object>
		<name>3</name>
		<pose>Unspecified</pose>
		<truncated>0</truncated>
		<difficult>0</difficult>
		<occluded>0</occluded>
		<bndbox>
			<xmin>129</xmin>
			<xmax>164</xmax>
			<ymin>49</ymin>
			<ymax>85</ymax>
		</bndbox>
	</object>
	<object>
		<name>0</name>
		<pose>Unspecified</pose>
		<truncated>0</truncated>
		<difficult>0</difficult>
		<occluded>0</occluded>
		<bndbox>
			<xmin>151</xmin>
			<xmax>187</xmax>
			<ymin>74</ymin>
			<ymax>108</ymax>
		</bndbox>
	</object>
	<object>
		<name>5</name>
		<pose>Unspecified</pose>
		<truncated>0</truncated>
		<difficult>0</difficult>
		<occluded>0</occluded>
		<bndbox>
			<xmin>178</xmin>
			<xmax>217</xmax>
			<ymin>120</ymin>
			<ymax>153</ymax>
		</bndbox>
	</object>
</annotation>
