<annotation>
	<folder></folder>
	<filename>507801354_jpg.rf.cb8adc25bb4c7c4a7ceeafb868335a10.jpg</filename>
	<path>507801354_jpg.rf.cb8adc25bb4c7c4a7ceeafb868335a10.jpg</path>
	<source>
		<database>roboflow.ai</database>
	</source>
	<size>
		<width>416</width>
		<height>416</height>
		<depth>3</depth>
	</size>
	<segmented>0</segmented>
	<object>
		<name>14</name>
		<pose>Unspecified</pose>
		<truncated>0</truncated>
		<difficult>0</difficult>
		<occluded>0</occluded>
		<bndbox>
			<xmin>185</xmin>
			<xmax>213</xmax>
			<ymin>126</ymin>
			<ymax>147</ymax>
		</bndbox>
	</object>
	<object>
		<name>4</name>
		<pose>Unspecified</pose>
		<truncated>0</truncated>
		<difficult>0</difficult>
		<occluded>0</occluded>
		<bndbox>
			<xmin>199</xmin>
			<xmax>224</xmax>
			<ymin>144</ymin>
			<ymax>164</ymax>
		</bndbox>
	</object>
	<object>
		<name>5</name>
		<pose>Unspecified</pose>
		<truncated>0</truncated>
		<difficult>0</difficult>
		<occluded>0</occluded>
		<bndbox>
			<xmin>209</xmin>
			<xmax>236</xmax>
			<ymin>173</ymin>
			<ymax>195</ymax>
		</bndbox>
	</object>
</annotation>
