<annotation>
	<folder></folder>
	<filename>548944723_jpg.rf.6e8f053b2cdcd573a5de08fb09d986b4.jpg</filename>
	<path>548944723_jpg.rf.6e8f053b2cdcd573a5de08fb09d986b4.jpg</path>
	<source>
		<database>roboflow.ai</database>
	</source>
	<size>
		<width>416</width>
		<height>416</height>
		<depth>3</depth>
	</size>
	<segmented>0</segmented>
	<object>
		<name>13</name>
		<pose>Unspecified</pose>
		<truncated>0</truncated>
		<difficult>0</difficult>
		<occluded>0</occluded>
		<bndbox>
			<xmin>170</xmin>
			<xmax>195</xmax>
			<ymin>128</ymin>
			<ymax>152</ymax>
		</bndbox>
	</object>
	<object>
		<name>9</name>
		<pose>Unspecified</pose>
		<truncated>0</truncated>
		<difficult>0</difficult>
		<occluded>0</occluded>
		<bndbox>
			<xmin>201</xmin>
			<xmax>234</xmax>
			<ymin>140</ymin>
			<ymax>177</ymax>
		</bndbox>
	</object>
	<object>
		<name>5</name>
		<pose>Unspecified</pose>
		<truncated>0</truncated>
		<difficult>0</difficult>
		<occluded>0</occluded>
		<bndbox>
			<xmin>232</xmin>
			<xmax>270</xmax>
			<ymin>165</ymin>
			<ymax>202</ymax>
		</bndbox>
	</object>
</annotation>
