<annotation>
	<folder></folder>
	<filename>561061525_jpg.rf.dafacc62fdeced93e56e925fa4d3cf63.jpg</filename>
	<path>561061525_jpg.rf.dafacc62fdeced93e56e925fa4d3cf63.jpg</path>
	<source>
		<database>roboflow.ai</database>
	</source>
	<size>
		<width>416</width>
		<height>416</height>
		<depth>3</depth>
	</size>
	<segmented>0</segmented>
	<object>
		<name>10</name>
		<pose>Unspecified</pose>
		<truncated>0</truncated>
		<difficult>0</difficult>
		<occluded>0</occluded>
		<bndbox>
			<xmin>199</xmin>
			<xmax>234</xmax>
			<ymin>155</ymin>
			<ymax>190</ymax>
		</bndbox>
	</object>
	<object>
		<name>12</name>
		<pose>Unspecified</pose>
		<truncated>0</truncated>
		<difficult>0</difficult>
		<occluded>0</occluded>
		<bndbox>
			<xmin>239</xmin>
			<xmax>270</xmax>
			<ymin>162</ymin>
			<ymax>194</ymax>
		</bndbox>
	</object>
	<object>
		<name>12</name>
		<pose>Unspecified</pose>
		<truncated>0</truncated>
		<difficult>0</difficult>
		<occluded>0</occluded>
		<bndbox>
			<xmin>283</xmin>
			<xmax>318</xmax>
			<ymin>177</ymin>
			<ymax>208</ymax>
		</bndbox>
	</object>
</annotation>
