<annotation>
	<folder></folder>
	<filename>616268768_jpg.rf.8acd12d6cba9ff9362bc13e5badc6ee9.jpg</filename>
	<path>616268768_jpg.rf.8acd12d6cba9ff9362bc13e5badc6ee9.jpg</path>
	<source>
		<database>roboflow.ai</database>
	</source>
	<size>
		<width>416</width>
		<height>416</height>
		<depth>3</depth>
	</size>
	<segmented>0</segmented>
	<object>
		<name>14</name>
		<pose>Unspecified</pose>
		<truncated>0</truncated>
		<difficult>0</difficult>
		<occluded>0</occluded>
		<bndbox>
			<xmin>222</xmin>
			<xmax>243</xmax>
			<ymin>108</ymin>
			<ymax>132</ymax>
		</bndbox>
	</object>
	<object>
		<name>6</name>
		<pose>Unspecified</pose>
		<truncated>0</truncated>
		<difficult>0</difficult>
		<occluded>0</occluded>
		<bndbox>
			<xmin>251</xmin>
			<xmax>269</xmax>
			<ymin>110</ymin>
			<ymax>133</ymax>
		</bndbox>
	</object>
	<object>
		<name>4</name>
		<pose>Unspecified</pose>
		<truncated>0</truncated>
		<difficult>0</difficult>
		<occluded>0</occluded>
		<bndbox>
			<xmin>269</xmin>
			<xmax>290</xmax>
			<ymin>117</ymin>
			<ymax>140</ymax>
		</bndbox>
	</object>
</annotation>
