<annotation>
	<folder></folder>
	<filename>624109182_jpg.rf.7c80aa0a7d0010c7c62d2a0ad564d00c.jpg</filename>
	<path>624109182_jpg.rf.7c80aa0a7d0010c7c62d2a0ad564d00c.jpg</path>
	<source>
		<database>roboflow.ai</database>
	</source>
	<size>
		<width>416</width>
		<height>416</height>
		<depth>3</depth>
	</size>
	<segmented>0</segmented>
	<object>
		<name>6</name>
		<pose>Unspecified</pose>
		<truncated>0</truncated>
		<difficult>0</difficult>
		<occluded>0</occluded>
		<bndbox>
			<xmin>191</xmin>
			<xmax>213</xmax>
			<ymin>226</ymin>
			<ymax>251</ymax>
		</bndbox>
	</object>
	<object>
		<name>7</name>
		<pose>Unspecified</pose>
		<truncated>0</truncated>
		<difficult>0</difficult>
		<occluded>0</occluded>
		<bndbox>
			<xmin>219</xmin>
			<xmax>239</xmax>
			<ymin>225</ymin>
			<ymax>248</ymax>
		</bndbox>
	</object>
	<object>
		<name>10</name>
		<pose>Unspecified</pose>
		<truncated>0</truncated>
		<difficult>0</difficult>
		<occluded>0</occluded>
		<bndbox>
			<xmin>249</xmin>
			<xmax>272</xmax>
			<ymin>230</ymin>
			<ymax>251</ymax>
		</bndbox>
	</object>
</annotation>
