<annotation>
	<folder></folder>
	<filename>625457871_jpg.rf.484823c28f097cb1eac086d10041022b.jpg</filename>
	<path>625457871_jpg.rf.484823c28f097cb1eac086d10041022b.jpg</path>
	<source>
		<database>roboflow.ai</database>
	</source>
	<size>
		<width>416</width>
		<height>416</height>
		<depth>3</depth>
	</size>
	<segmented>0</segmented>
	<object>
		<name>11</name>
		<pose>Unspecified</pose>
		<truncated>0</truncated>
		<difficult>0</difficult>
		<occluded>0</occluded>
		<bndbox>
			<xmin>217</xmin>
			<xmax>242</xmax>
			<ymin>133</ymin>
			<ymax>156</ymax>
		</bndbox>
	</object>
	<object>
		<name>11</name>
		<pose>Unspecified</pose>
		<truncated>0</truncated>
		<difficult>0</difficult>
		<occluded>0</occluded>
		<bndbox>
			<xmin>239</xmin>
			<xmax>265</xmax>
			<ymin>149</ymin>
			<ymax>173</ymax>
		</bndbox>
	</object>
	<object>
		<name>13</name>
		<pose>Unspecified</pose>
		<truncated>0</truncated>
		<difficult>0</difficult>
		<occluded>0</occluded>
		<bndbox>
			<xmin>263</xmin>
			<xmax>281</xmax>
			<ymin>179</ymin>
			<ymax>196</ymax>
		</bndbox>
	</object>
</annotation>
