<annotation>
	<folder></folder>
	<filename>636817934_jpg.rf.f2ecd695a72958241b901dba4cdddf32.jpg</filename>
	<path>636817934_jpg.rf.f2ecd695a72958241b901dba4cdddf32.jpg</path>
	<source>
		<database>roboflow.ai</database>
	</source>
	<size>
		<width>416</width>
		<height>416</height>
		<depth>3</depth>
	</size>
	<segmented>0</segmented>
	<object>
		<name>5</name>
		<pose>Unspecified</pose>
		<truncated>0</truncated>
		<difficult>0</difficult>
		<occluded>0</occluded>
		<bndbox>
			<xmin>199</xmin>
			<xmax>237</xmax>
			<ymin>120</ymin>
			<ymax>156</ymax>
		</bndbox>
	</object>
	<object>
		<name>4</name>
		<pose>Unspecified</pose>
		<truncated>0</truncated>
		<difficult>0</difficult>
		<occluded>0</occluded>
		<bndbox>
			<xmin>222</xmin>
			<xmax>259</xmax>
			<ymin>159</ymin>
			<ymax>187</ymax>
		</bndbox>
	</object>
	<object>
		<name>1</name>
		<pose>Unspecified</pose>
		<truncated>0</truncated>
		<difficult>0</difficult>
		<occluded>0</occluded>
		<bndbox>
			<xmin>243</xmin>
			<xmax>278</xmax>
			<ymin>202</ymin>
			<ymax>230</ymax>
		</bndbox>
	</object>
</annotation>
