<annotation>
	<folder></folder>
	<filename>674661190_jpg.rf.39d72cfc7e7a1f83af32d85b8fe11de9.jpg</filename>
	<path>674661190_jpg.rf.39d72cfc7e7a1f83af32d85b8fe11de9.jpg</path>
	<source>
		<database>roboflow.ai</database>
	</source>
	<size>
		<width>416</width>
		<height>416</height>
		<depth>3</depth>
	</size>
	<segmented>0</segmented>
	<object>
		<name>14</name>
		<pose>Unspecified</pose>
		<truncated>0</truncated>
		<difficult>0</difficult>
		<occluded>0</occluded>
		<bndbox>
			<xmin>91</xmin>
			<xmax>111</xmax>
			<ymin>160</ymin>
			<ymax>188</ymax>
		</bndbox>
	</object>
	<object>
		<name>4</name>
		<pose>Unspecified</pose>
		<truncated>0</truncated>
		<difficult>0</difficult>
		<occluded>0</occluded>
		<bndbox>
			<xmin>119</xmin>
			<xmax>139</xmax>
			<ymin>154</ymin>
			<ymax>178</ymax>
		</bndbox>
	</object>
	<object>
		<name>5</name>
		<pose>Unspecified</pose>
		<truncated>0</truncated>
		<difficult>0</difficult>
		<occluded>0</occluded>
		<bndbox>
			<xmin>140</xmin>
			<xmax>160</xmax>
			<ymin>153</ymin>
			<ymax>177</ymax>
		</bndbox>
	</object>
</annotation>
