<annotation>
	<folder></folder>
	<filename>683523423_jpg.rf.892f8af0365406bfdb5443bf3b226e72.jpg</filename>
	<path>683523423_jpg.rf.892f8af0365406bfdb5443bf3b226e72.jpg</path>
	<source>
		<database>roboflow.ai</database>
	</source>
	<size>
		<width>416</width>
		<height>416</height>
		<depth>3</depth>
	</size>
	<segmented>0</segmented>
	<object>
		<name>13</name>
		<pose>Unspecified</pose>
		<truncated>0</truncated>
		<difficult>0</difficult>
		<occluded>0</occluded>
		<bndbox>
			<xmin>205</xmin>
			<xmax>232</xmax>
			<ymin>172</ymin>
			<ymax>193</ymax>
		</bndbox>
	</object>
	<object>
		<name>4</name>
		<pose>Unspecified</pose>
		<truncated>0</truncated>
		<difficult>0</difficult>
		<occluded>0</occluded>
		<bndbox>
			<xmin>219</xmin>
			<xmax>243</xmax>
			<ymin>186</ymin>
			<ymax>207</ymax>
		</bndbox>
	</object>
	<object>
		<name>14</name>
		<pose>Unspecified</pose>
		<truncated>0</truncated>
		<difficult>0</difficult>
		<occluded>0</occluded>
		<bndbox>
			<xmin>244</xmin>
			<xmax>272</xmax>
			<ymin>220</ymin>
			<ymax>241</ymax>
		</bndbox>
	</object>
</annotation>
