<annotation>
	<folder></folder>
	<filename>790306829_jpg.rf.3b6afdc1d3f2e860a12fb7540f7fbced.jpg</filename>
	<path>790306829_jpg.rf.3b6afdc1d3f2e860a12fb7540f7fbced.jpg</path>
	<source>
		<database>roboflow.ai</database>
	</source>
	<size>
		<width>416</width>
		<height>416</height>
		<depth>3</depth>
	</size>
	<segmented>0</segmented>
	<object>
		<name>4</name>
		<pose>Unspecified</pose>
		<truncated>0</truncated>
		<difficult>0</difficult>
		<occluded>0</occluded>
		<bndbox>
			<xmin>101</xmin>
			<xmax>132</xmax>
			<ymin>59</ymin>
			<ymax>92</ymax>
		</bndbox>
	</object>
	<object>
		<name>2</name>
		<pose>Unspecified</pose>
		<truncated>0</truncated>
		<difficult>0</difficult>
		<occluded>0</occluded>
		<bndbox>
			<xmin>138</xmin>
			<xmax>170</xmax>
			<ymin>67</ymin>
			<ymax>101</ymax>
		</bndbox>
	</object>
	<object>
		<name>9</name>
		<pose>Unspecified</pose>
		<truncated>0</truncated>
		<difficult>0</difficult>
		<occluded>0</occluded>
		<bndbox>
			<xmin>173</xmin>
			<xmax>204</xmax>
			<ymin>83</ymin>
			<ymax>118</ymax>
		</bndbox>
	</object>
</annotation>
