<annotation>
	<folder></folder>
	<filename>820916890_jpg.rf.fd802e968ad59b23a002bd66137a0028.jpg</filename>
	<path>820916890_jpg.rf.fd802e968ad59b23a002bd66137a0028.jpg</path>
	<source>
		<database>roboflow.ai</database>
	</source>
	<size>
		<width>416</width>
		<height>416</height>
		<depth>3</depth>
	</size>
	<segmented>0</segmented>
	<object>
		<name>11</name>
		<pose>Unspecified</pose>
		<truncated>0</truncated>
		<difficult>0</difficult>
		<occluded>0</occluded>
		<bndbox>
			<xmin>136</xmin>
			<xmax>172</xmax>
			<ymin>51</ymin>
			<ymax>84</ymax>
		</bndbox>
	</object>
	<object>
		<name>13</name>
		<pose>Unspecified</pose>
		<truncated>0</truncated>
		<difficult>0</difficult>
		<occluded>0</occluded>
		<bndbox>
			<xmin>176</xmin>
			<xmax>201</xmax>
			<ymin>76</ymin>
			<ymax>100</ymax>
		</bndbox>
	</object>
	<object>
		<name>12</name>
		<pose>Unspecified</pose>
		<truncated>0</truncated>
		<difficult>0</difficult>
		<occluded>0</occluded>
		<bndbox>
			<xmin>206</xmin>
			<xmax>247</xmax>
			<ymin>114</ymin>
			<ymax>139</ymax>
		</bndbox>
	</object>
</annotation>
