<annotation>
	<folder></folder>
	<filename>874453291_jpg.rf.18a15fcf8054a91f1086f94b2a95dc81.jpg</filename>
	<path>874453291_jpg.rf.18a15fcf8054a91f1086f94b2a95dc81.jpg</path>
	<source>
		<database>roboflow.ai</database>
	</source>
	<size>
		<width>416</width>
		<height>416</height>
		<depth>3</depth>
	</size>
	<segmented>0</segmented>
	<object>
		<name>14</name>
		<pose>Unspecified</pose>
		<truncated>0</truncated>
		<difficult>0</difficult>
		<occluded>0</occluded>
		<bndbox>
			<xmin>79</xmin>
			<xmax>100</xmax>
			<ymin>199</ymin>
			<ymax>227</ymax>
		</bndbox>
	</object>
	<object>
		<name>3</name>
		<pose>Unspecified</pose>
		<truncated>0</truncated>
		<difficult>0</difficult>
		<occluded>0</occluded>
		<bndbox>
			<xmin>99</xmin>
			<xmax>121</xmax>
			<ymin>192</ymin>
			<ymax>217</ymax>
		</bndbox>
	</object>
	<object>
		<name>9</name>
		<pose>Unspecified</pose>
		<truncated>0</truncated>
		<difficult>0</difficult>
		<occluded>0</occluded>
		<bndbox>
			<xmin>141</xmin>
			<xmax>160</xmax>
			<ymin>187</ymin>
			<ymax>211</ymax>
		</bndbox>
	</object>
</annotation>
