<annotation>
	<folder></folder>
	<filename>961492585_jpg.rf.14ca8de4d3ab7cfe08d4c73be045d040.jpg</filename>
	<path>961492585_jpg.rf.14ca8de4d3ab7cfe08d4c73be045d040.jpg</path>
	<source>
		<database>roboflow.ai</database>
	</source>
	<size>
		<width>416</width>
		<height>416</height>
		<depth>3</depth>
	</size>
	<segmented>0</segmented>
	<object>
		<name>12</name>
		<pose>Unspecified</pose>
		<truncated>0</truncated>
		<difficult>0</difficult>
		<occluded>0</occluded>
		<bndbox>
			<xmin>92</xmin>
			<xmax>112</xmax>
			<ymin>156</ymin>
			<ymax>178</ymax>
		</bndbox>
	</object>
	<object>
		<name>0</name>
		<pose>Unspecified</pose>
		<truncated>0</truncated>
		<difficult>0</difficult>
		<occluded>0</occluded>
		<bndbox>
			<xmin>114</xmin>
			<xmax>135</xmax>
			<ymin>162</ymin>
			<ymax>185</ymax>
		</bndbox>
	</object>
	<object>
		<name>0</name>
		<pose>Unspecified</pose>
		<truncated>0</truncated>
		<difficult>0</difficult>
		<occluded>0</occluded>
		<bndbox>
			<xmin>145</xmin>
			<xmax>168</xmax>
			<ymin>178</ymin>
			<ymax>202</ymax>
		</bndbox>
	</object>
</annotation>
